README.rst
setup.cfg
setup.py
sdafile/__init__.py
sdafile/cell_inserter.py
sdafile/character_inserter.py
sdafile/exceptions.py
sdafile/extract.py
sdafile/file_inserter.py
sdafile/logical_inserter.py
sdafile/numeric_inserter.py
sdafile/record_inserter.py
sdafile/sda_file.py
sdafile/structure_inserter.py
sdafile/testing.py
sdafile/utils.py
sdafile/version.py
sdafile.egg-info/PKG-INFO
sdafile.egg-info/SOURCES.txt
sdafile.egg-info/dependency_links.txt
sdafile.egg-info/requires.txt
sdafile.egg-info/top_level.txt
sdafile.egg-info/zip-safe