Metadata-Version: 1.1
Name: sdafile
Version: 0.2.0
Summary: Tools for reading, writing, altering, and inspecting Sandia Data Archive (SDA) files.
Home-page: https://github.com/enthought/sandia-data-archive
Author: Sandia National Laboratories
Author-email: cfarrow@enthought.com
License: BSD
Platform: Windows
Platform: Linux
Platform: Mac OS-X
Platform: Unix
Platform: Solaris
Classifier: Development Status :: 2 - Pre-Alpha
Classifier: Intended Audience :: Developers
Classifier: Intended Audience :: Science/Research
Classifier: License :: OSI Approved :: BSD License
Classifier: Operating System :: MacOS
Classifier: Operating System :: Microsoft :: Windows
Classifier: Operating System :: OS Independent
Classifier: Operating System :: POSIX
Classifier: Operating System :: Unix
Classifier: Programming Language :: Python
Classifier: Topic :: Scientific/Engineering
Classifier: Topic :: Software Development
Classifier: Topic :: Software Development :: Libraries
